<?xml version="1.0"?>
<tasks>
  <task>
    <id>1</id>
    <desc>COMP1234 assignment</desc>
    <priority>2</priority>
    <size>2</size>
    <group>2</group>
    <deadline>20170219</deadline>
    <status>1</status>
    <flag>0</flag>
    <submit>Update the TODO task</submit>
  </task>
  <task>
    <id>2</id>
    <desc>Mow the lawn</desc>
    <priority>2</priority>
    <size>2</size>
    <group>1</group>
    <deadline/>
    <status>2</status>
    <flag>0</flag>
  </task>
  <task>
    <id>3</id>
    <desc>Wash the car</desc>
    <priority>2</priority>
    <size>2</size>
    <group>1</group>
    <deadline/>
    <status>0</status>
    <flag>0</flag>
  </task>
  <task>
    <id>4</id>
    <desc>Paint the fence</desc>
    <priority>1</priority>
    <size>2</size>
    <group>1</group>
    <deadline/>
    <status>0</status>
    <flag>0</flag>
  </task>
  <task>
    <id>5</id>
    <desc>Intramural hockey game</desc>
    <priority>1</priority>
    <size>2</size>
    <group>4</group>
    <deadline/>
    <status>0</status>
    <flag>0</flag>
  </task>
  <task>
    <id>6</id>
    <desc>Canucks hockey game</desc>
    <priority>3</priority>
    <size>3</size>
    <group>4</group>
    <deadline>20170305</deadline>
    <priority>1</priority>
    <size>3</size>
    <group>3</group>
    <deadline>20161231</deadline>
    <status>1</status>
    <flag>0</flag>
  </task>
  <task>
    <id>9</id>
    <desc>Hit the gym</desc>
    <priority>2</priority>
    <size>1</size>
    <group>4</group>
    <deadline/>
    <status>0</status>
    <flag>0</flag>
  </task>
  <task>
    <id>10</id>
    <desc>Pay bills</desc>
    <priority>3</priority>
    <size>1</size>
    <group>1</group>
    <deadline/>
    <status>0</status>
    <flag>0</flag>
  </task>
  <task>
    <id>11</id>
    <desc>Meet George</desc>
    <priority>2</priority>
    <size>1</size>
    <group>1</group>
    <deadline/>
    <status>0</status>
    <flag>0</flag>
  </task>
  <task>
    <id>12</id>
    <desc>Buy milk bread</desc>
    <priority>2</priority>
    <size>1</size>
    <group>1</group>
    <deadline/>
    <status>0</status>
    <flag>1</flag>
  </task>
  <task>
    <id>13</id>
    <desc>Read War Peace</desc>
    <priority>1</priority>
    <size>3</size>
    <group>1</group>
    <deadline/>
    <status>0</status>
    <flag>0</flag>
  </task>
  <task>
    <id>14</id>
    <desc>Organize the study</desc>
    <priority>1</priority>
    <size>4</size>
    <group>1</group>
    <deadline>20170219</deadline>
    <status>1</status>
    <flag>0</flag>
  </task>
</tasks>
